yagot/__init__.py
yagot/_decorators.py
yagot/_garbagetracker.py
yagot/_version.py
yagot_pytest/__init__.py
yagot_pytest/plugin.py
yagot-0.5.0.dist-info/LICENSE
yagot-0.5.0.dist-info/METADATA
yagot-0.5.0.dist-info/WHEEL
yagot-0.5.0.dist-info/entry_points.txt
yagot-0.5.0.dist-info/top_level.txt
yagot-0.5.0.dist-info/zip-safe
yagot-0.5.0.dist-info/RECORD
