Metadata-Version: 2.1
Name: yagot
Version: 0.5.0
Summary: Yet Another Garbage Object Tracker for Python
Home-page: https://github.com/andy-maier/python-yagot
Author: Andreas Maier
Author-email: andreas.r.maier@gmx.de
Maintainer: Andreas Maier
Maintainer-email: andreas.r.maier@gmx.de
License: Apache Software License 2.0
Project-URL: Bug Tracker, https://github.com/andy-maier/python-yagot/issues
Project-URL: Documentation, https://yagot.readthedocs.io/en/latest/
Project-URL: Source Code, https://github.com/andy-maier/python-yagot
Platform: any
Classifier: Development Status :: 4 - Beta
Classifier: Environment :: Console
Classifier: Intended Audience :: Developers
Classifier: License :: OSI Approved :: Apache Software License
Classifier: Operating System :: OS Independent
Classifier: Programming Language :: Python :: 2
Classifier: Programming Language :: Python :: 2.7
Classifier: Programming Language :: Python :: 3
Classifier: Programming Language :: Python :: 3.4
Classifier: Programming Language :: Python :: 3.5
Classifier: Programming Language :: Python :: 3.6
Classifier: Programming Language :: Python :: 3.7
Classifier: Programming Language :: Python :: 3.8
Classifier: Topic :: Software Development :: Libraries :: Python Modules
Requires-Python: >=2.7, !=3.0.*, !=3.1.*, !=3.2.*, !=3.3.*
Requires-Dist: six (>=1.10.0)
